{"width":1025,"SubTexture":[{"width":465,"y":545,"height":565,"name":"smoke","x":1},{"width":783,"y":1,"height":542,"name":"gunfire","x":1},{"width":300,"y":545,"height":612,"name":"gun","x":468},{"width":230,"y":1,"height":230,"name":"gun2","x":786},{"width":257,"y":1112,"height":257,"name":"gun3","x":1},{"width":67,"y":233,"height":66,"name":"bullet","x":786},{"width":240,"y":545,"height":336,"name":"gun1","x":770},{"width":5,"y":1,"height":5,"name":"p","x":1018}],"height":1371,"name":"handgun","imagePath":"handgun_tex.png"}